argusquery_api/__init__.py
argusquery_api/auth.py
argusquery_api/create_file_category_and_app.py
argusquery_api/semantic_search.py
argusquery_api-0.0.1.dist-info/LICENSE
argusquery_api-0.0.1.dist-info/METADATA
argusquery_api-0.0.1.dist-info/WHEEL
argusquery_api-0.0.1.dist-info/RECORD
