Metadata-Version: 2.3
Name: argusquery-api
Version: 0.0.1
Summary: A Python API for executing backend admin workflows for ArgusQuery
License: MIT
Author: Kiran de Silva
Author-email: kiran.desilva@argusanalytics.io
Requires-Python: >=3.10
Classifier: License :: OSI Approved :: MIT License
Classifier: Programming Language :: Python :: 3
Classifier: Programming Language :: Python :: 3.10
Classifier: Programming Language :: Python :: 3.11
Classifier: Programming Language :: Python :: 3.12
Classifier: Programming Language :: Python :: 3.13
Classifier: Topic :: Scientific/Engineering :: Artificial Intelligence
Classifier: Topic :: Software Development :: Libraries :: Python Modules
Requires-Dist: pydantic (==2.10.6)
Requires-Dist: requests (==2.31.0)
Project-URL: Homepage, https://gitlab.com/argusquery/api
Project-URL: Repository, https://gitlab.com/argusquery/api
